src/__init__.py
src/harlsk.py
harlsk-0.0.13.dist-info/METADATA
harlsk-0.0.13.dist-info/WHEEL
harlsk-0.0.13.dist-info/top_level.txt
harlsk-0.0.13.dist-info/RECORD
